openload_dl/__init__.py
openload_dl/__version__.py
openload_dl/openload_dl.py
openload_dl/script.py
openload_dl/utils.py
openload_dl-2.0.1.dist-info/LICENSE
openload_dl-2.0.1.dist-info/METADATA
openload_dl-2.0.1.dist-info/WHEEL
openload_dl-2.0.1.dist-info/entry_points.txt
openload_dl-2.0.1.dist-info/top_level.txt
openload_dl-2.0.1.dist-info/RECORD
