Metadata-Version: 2.1
Name: openload-dl
Version: 2.0.1
Summary: openload_dl is a python library and CLI tool which makes easy to download files from openload.co
Home-page: https://github.com/glumia/openload_dl
Author: Giuseppe Lumia
Author-email: glumia@protonmail.com
License: UNKNOWN
Platform: UNKNOWN
Classifier: Programming Language :: Python :: 3
Classifier: License :: OSI Approved :: MIT License
Classifier: Operating System :: OS Independent
Requires-Python: >=3.6
Requires-Dist: requests
Requires-Dist: selenium
Requires-Dist: click
Requires-Dist: tqdm
